herewalletbot/__init__.py
herewalletbot/herewalletbot.py
herewalletbot-1.0.dist-info/LICENSE
herewalletbot-1.0.dist-info/METADATA
herewalletbot-1.0.dist-info/WHEEL
herewalletbot-1.0.dist-info/entry_points.txt
herewalletbot-1.0.dist-info/top_level.txt
herewalletbot-1.0.dist-info/RECORD
