Metadata-Version: 2.1
Name: herewalletbot
Version: 1.0
Summary: Automate your interactions with the HotWallet web application using Selenium.
Home-page: https://github.com/vannszs/HotWalletBot
Author: vannszs
Author-email: bevansatria@gmail.com
License-File: LICENSE
